simple_background_task/__init__.py
simple_background_task/task.py
simple_background_task/integrate/__init__.py
simple_background_task/integrate/django/__init__.py
simple_background_task/integrate/django/apps.py
simple_background_task/queue/__init__.py
simple_background_task/queue/interface.py
simple_background_task/queue/memory.py
simple_background_task-0.1.1.dist-info/METADATA
simple_background_task-0.1.1.dist-info/WHEEL
simple_background_task-0.1.1.dist-info/top_level.txt
simple_background_task-0.1.1.dist-info/RECORD
