Metadata-Version: 2.1
Name: simple-background-task
Version: 0.1.1
Summary: A background task base on thread,easy to integer with any framework
Home-page: https://github.com/igzhang/simple_background_task.git
Author: fallthrough
Author-email: rainbroadcast@gmail.com
License: UNKNOWN
Platform: UNKNOWN
Classifier: Programming Language :: Python
Classifier: Programming Language :: Python :: 3
Provides-Extra: rocketmq
